navargus/__init__.py
navargus/feeder.py
navargus/glue.py
nav_argus_glue-0.8.2.dist-info/METADATA
nav_argus_glue-0.8.2.dist-info/WHEEL
nav_argus_glue-0.8.2.dist-info/entry_points.txt
nav_argus_glue-0.8.2.dist-info/top_level.txt
nav_argus_glue-0.8.2.dist-info/RECORD
