Metadata-Version: 2.4
Name: nav-argus-glue
Version: 0.8.2
Summary: An Argus glue service for Network Administration Visualized
Author-email: Morten Brekkevold <morten.brekkevold@sikt.no>
License-Expression: GPL-3.0-only
Project-URL: GitHub, https://github.com/Uninett/nav-argus-glue
Project-URL: Argus, https://network.geant.org/argus/
Project-URL: NAV, http://nav.uninett.no/
Keywords: api,argus,client
Classifier: Programming Language :: Python :: 3
Classifier: Programming Language :: Python :: 3.9
Requires-Python: >=3.9
Requires-Dist: argus-api-client>=0.5.0
Requires-Dist: pyaml
